tvmaze/api.py
tvmaze/character.py
tvmaze/client.py
tvmaze/episode.py
tvmaze/expections.py
tvmaze/models.py
tvmaze/network.py
tvmaze/people.py
tvmaze/schedule.py
tvmaze/search.py
tvmaze/show.py
tvmaze/version.py
tvmaze/webchannel.py
py_tvmaze_api-2021.5.6.dist-info/entry_points.txt
py_tvmaze_api-2021.5.6.dist-info/LICENSE
py_tvmaze_api-2021.5.6.dist-info/WHEEL
py_tvmaze_api-2021.5.6.dist-info/METADATA
py_tvmaze_api-2021.5.6.dist-info/RECORD
