Metadata-Version: 2.1
Name: py-tvmaze-api
Version: 2021.5.6
Summary: A Python client for the TvMaze API.
Home-page: https://github.com/sickchill/python-tvmaze
License: MIT
Keywords: tvmaze,library
Author: Yakup Adaklı
Author-email: yakup.adakli@gmail.com
Requires-Python: >=3.6
Classifier: Development Status :: 3 - Alpha
Classifier: Intended Audience :: System Administrators
Classifier: License :: OSI Approved :: MIT License
Classifier: Operating System :: OS Independent
Classifier: Programming Language :: Python :: 3
Classifier: Programming Language :: Python :: 3.6
Classifier: Programming Language :: Python :: 3.7
Classifier: Programming Language :: Python :: 3.8
Classifier: Programming Language :: Python :: 3.9
Classifier: Programming Language :: Python :: 3.10
Classifier: Programming Language :: Python :: 3
Classifier: Programming Language :: Python :: 3 :: Only
Classifier: Programming Language :: Python :: 3.6
Classifier: Programming Language :: Python :: 3.7
Classifier: Programming Language :: Python :: 3.8
Classifier: Programming Language :: Python :: 3.9
Classifier: Topic :: Multimedia :: Video
Requires-Dist: requests (>=2.25.1,<3.0.0)
Project-URL: Repository, https://github.com/sickchill/python-tvmaze
